CHANGES.md
LICENSE
MANIFEST.in
README.md
setup.cfg
setup.py
poinspection/__init__.py
poinspection/poinspection.py
poinspection.egg-info/PKG-INFO
poinspection.egg-info/SOURCES.txt
poinspection.egg-info/dependency_links.txt
poinspection.egg-info/requires.txt
poinspection.egg-info/top_level.txt
poinspection.egg-info/zip-safe