Metadata-Version: 1.0
Name: poinspection
Version: 0.0.2
Summary: Python inspection magic functions for ipython
Home-page: https://github.com/luismmontielg/poinspection
Author: Luis Montiel
Author-email: luismmontielg@gmail.com
License: Creative Commons CC0 1.0 Universal (CC0 1.0) Public Domain Dedication
Keywords: ipython
Platform: UNKNOWN
Classifier: Programming Language :: Python
Classifier: Intended Audience :: Developers
Classifier: License :: CC0 1.0 Universal (CC0 1.0) Public Domain Dedication
Classifier: Operating System :: OS Independent
